{
    "projects":[
                {
                    "name": "Diabeatit",
                    "title": "Diabeatit",
                    "url": "dieabeatit",
                    "description": "Diabeatit <br> Android app that teaches kids about healthy eating.",
                    "img": "img/diabeatit.jpg",
                    "color": "#89a398",
                    "secondimg": "img/diabeatitplan.jpg",
                    "info": [
                        {
                            "title": "Role",
                            "content": "Software developer"
                        },
                        {
                            "title": "Design Tools",
                            "content": "Figma"
                        },
                        {
                            "title": "Development Tools",
                            "content": "Unity , #C"
                        },
                        {
                            "title": "Date",
                            "content": "September 2018 - December 2018"
                        }
                    ]
                    },{
                        "name": "LWCMP",
                        "title": "LWCMP",
                        "img": "img/lwcm.jpg",
                        "description": "LWCMPT<br>Data collection and visualtion web app.",
                        "url":"lwcmp",
                        "color": "#c3d7f3",
                        "secondimg": "img/lwcmplan.jpg",
                        "info": [
                            {
                                "title": "Role",
                                "content": "UX Researcher, Web development"
                            },
                            {
                                "title": "Design Tools",
                                "content": "Figma"
                            },
                            {
                                "title": "Development Tools",
                                "content": "HTML, CSS, JavaScript, Node.js(Express + Handlebars + Passport.js)"
                            },
                            {
                                "title": "Date",
                                "content": "April 2018 - June 2018"
                            }
                        ]
                        },{
                            "name": "NueroViz",
                            "title": "NueroViz",
                            "url": "nuero",
                            "description": "NueroViz <br> Web app prototype that tracks students’ study habits and dipsplays it to user.",
                            "img": "img/nuero.jpg",
                            "color": "#89a398",
                            "secondimg": "img/nueroplan.jpg",
                            "info": [
                                {
                                    "title": "Role",
                                    "content": "UX/UI Designer, Back-End development"
                                },
                                {
                                    "title": "Design Tools",
                                    "content": "Figma"
                                },
                                {
                                    "title": "Development Tools",
                                    "content": "HTML, CSS, JavaScript, Node.js(Express + Handlebars)"
                                },
                                {
                                    "title": "Date",
                                    "content": "April 2018 - June 2018"
                                }
                            ]
                            },{
                                "name": "Research",
                                "title": "Research",
                                "url": "memory",
                                "description": "Undergraduate Researcher<br> Vision and Memory Lab",
                                "img": "img/research.png",
                                "color": "#89a398",
                                "secondimg": "img/researchplan.jpg",
                                "info": [
                                    {
                                        "title": "Role",
                                        "content": "Software developer"
                                    },
                                    {
                                        "title": "Design Tools",
                                        "content": "Google Docs"
                                    },
                                    {
                                        "title": "Development Tools",
                                        "content": "MATLAB(Psychophysics Toolbox)"
                                    },
                                    {
                                        "title": "Date",
                                        "content": "September 2017 - December 2017"
                                    }
                                ]
                                }
    ]
}